gobo/__about__.py
gobo/__init__.py
gobo/corner_plot.py
gobo/palette.py
gobo/internal/__init__.py
gobo/internal/corner_plot.py
gobo/internal/logging.py
gobo/internal/palette.py
gobo-0.6.0.dist-info/METADATA
gobo-0.6.0.dist-info/WHEEL
gobo-0.6.0.dist-info/RECORD
