Metadata-Version: 2.3
Name: gobo
Version: 0.6.0
Author-email: golmschenk <greg@olmschenk.com>
Requires-Python: >=3.9
Requires-Dist: bokeh>=3.0.0
Requires-Dist: numpy>=2.0.0
Requires-Dist: pandas>=1.5.3
Requires-Dist: polars>=0.19.10
Requires-Dist: pytest>=7.1.3
Requires-Dist: scipy>=1.10.0
Requires-Dist: selenium>=4.0.0
Requires-Dist: typing-extensions
